opnsense_backup/__init__.py
opnsense_backup/__main__.py
opnsense_backup/cli.py
opnsense_backup-0.1.0.dist-info/licenses/LICENSE
opnsense_backup-0.1.0.dist-info/METADATA
opnsense_backup-0.1.0.dist-info/WHEEL
opnsense_backup-0.1.0.dist-info/entry_points.txt
opnsense_backup-0.1.0.dist-info/top_level.txt
opnsense_backup-0.1.0.dist-info/RECORD
