Metadata-Version: 2.4
Name: opnsense_backup
Version: 0.1.0
Summary: A simple tool to fetch backups from the OPNsense firewall
Author-email: Stanislav Meduna <stano@meduna.org>
Project-URL: Homepage, https://github.com/numo68/opnsense-backup
Project-URL: Bug Tracker, https://github.com/numo68/opnsense-backup/issues
Classifier: Programming Language :: Python :: 3
Classifier: License :: OSI Approved :: MIT License
Classifier: Operating System :: OS Independent
Requires-Python: >=3.10
License-File: LICENSE
Requires-Dist: PyYAML
Requires-Dist: schema
Requires-Dist: prometheus-client
Requires-Dist: httpx
Requires-Dist: PyCryptodome
Dynamic: license-file
